AUTHORS.txt
CHANGES.txt
LICENSE-GPL.txt
MANIFEST.in
README.rst
setup.cfg
setup.py
neo4jrestclient/__init__.py
neo4jrestclient/client.py
neo4jrestclient/constants.py
neo4jrestclient/exceptions.py
neo4jrestclient/iterable.py
neo4jrestclient/labels.py
neo4jrestclient/options.py
neo4jrestclient/query.py
neo4jrestclient/request.py
neo4jrestclient/traversals.py
neo4jrestclient/utils.py
neo4jrestclient.egg-info/PKG-INFO
neo4jrestclient.egg-info/SOURCES.txt
neo4jrestclient.egg-info/dependency_links.txt
neo4jrestclient.egg-info/not-zip-safe
neo4jrestclient.egg-info/requires.txt
neo4jrestclient.egg-info/top_level.txt
neo4jrestclient/tests/__init__.py
neo4jrestclient/tests/test_cache.py
neo4jrestclient/tests/test_exceptions.py
neo4jrestclient/tests/test_extensions.py
neo4jrestclient/tests/test_filters.py
neo4jrestclient/tests/test_graphdatabase.py
neo4jrestclient/tests/test_indices.py
neo4jrestclient/tests/test_labels.py
neo4jrestclient/tests/test_nodes.py
neo4jrestclient/tests/test_pickle.py
neo4jrestclient/tests/test_query.py
neo4jrestclient/tests/test_relationships.py
neo4jrestclient/tests/test_transactions.py
neo4jrestclient/tests/test_traversals.py