Metadata-Version: 1.1
Name: neo4jrestclient
Version: 2.0.1
Summary: Object-oriented Python library to interact with Neo4j standalone REST server
Home-page: https://github.com/versae/neo4j-rest-client
Author: Javier de la Rosa
Author-email: versae@gmail.com
License: GPL 3
Keywords: neo4j graph graphdb graphdatabase database rest client driver
Platform: UNKNOWN
Classifier: Development Status :: 4 - Beta
Classifier: Intended Audience :: Developers
Classifier: License :: OSI Approved :: GNU General Public License (GPL)
Classifier: Operating System :: OS Independent
Classifier: Programming Language :: Python
Classifier: Programming Language :: Python :: 2
Classifier: Programming Language :: Python :: 3
Classifier: Topic :: Internet :: WWW/HTTP
